[
    {
      "id": "lll2xt8vlikyuzzhyx",
      "products": []
    },
    {
      "id": "lllcakmmymqkxpsgj7",
      "products": []
    },
    {
      "id": "llle79j3s94vz6vf9qm",
      "products": [
        {
          "product": "2",
          "quantity": 4
        },
        {
          "product": "1",
          "quantity": 2
        },
        {
          "product": "5",
          "quantity": 1
        },
        {
          "product": "8",
          "quantity": 1
        },
        {
          "product": "3",
          "quantity": 1
        },
        {
          "product": "4",
          "quantity": 1
        }
      ]
    }
  ]